{
  "items": [
    {
      "report_date": "2026-05-15",
      "fingerprint": "562d40a2d88cfc753a3f6fd3fd433ec6b9cf94c3",
      "title": "感知中国活力：西南麦区迎来大面积收获",
      "url": "https://news.cctv.com/2026/05/16/ARTIJrg2CzWLazyJLclTykCA260515.shtml",
      "category": "top_politics",
      "source": "央视网"
    },
    {
      "report_date": "2026-05-15",
      "fingerprint": "41b3e83f773c926f6e8d652daca1681f78ff3edc",
      "title": "习近平同美国总统特朗普在中南海小范围会晤",
      "url": "https://www.gov.cn/yaowen/liebiao/202605/content_7068921.htm",
      "category": "policy",
      "source": "中国政府网"
    },
    {
      "report_date": "2026-05-15",
      "fingerprint": "a4d32f0c30d5dcb99ca53a90f8c508dcf87bd1d4",
      "title": "2026年一季度我国数字产业收入同比增长12.9%",
      "url": "https://www.gov.cn/zhengce/jiedu/tujie/202605/content_7068806.htm",
      "category": "policy",
      "source": "中国政府网"
    },
    {
      "report_date": "2026-05-15",
      "fingerprint": "914037b7344b269d260db9080849a6087d869f7f",
      "title": "市政府召开常务会议 研究一季度营商环境监测评价报告等事项 市长殷勇主持会议",
      "url": "https://www.beijing.gov.cn/ywdt/hyxx/szf/202605/t20260515_4651668.html",
      "category": "regional",
      "source": "首都之窗"
    },
    {
      "report_date": "2026-05-15",
      "fingerprint": "75008a9e1fe368469bda495f8a701d87efb4a3e7",
      "title": "黄浦区人民政府办公室关于印发《黄浦区全面深化成本预算绩效管理改革工作方案（2026—2028年）》的通知",
      "url": "https://www.shanghai.gov.cn/nw12344/20260515/cc10d6b7c5bd4b7dbbf9672523d665ca.html",
      "category": "regional",
      "source": "上海市人民政府"
    },
    {
      "report_date": "2026-05-15",
      "fingerprint": "8809f28d9acfd2db0663a750b64c706da0337364",
      "title": "市政府新闻发布会介绍并解读《深化“一网通办”改革 打造“高效办成一件事”最佳体验地行动方案》等有关内容",
      "url": "https://www.shanghai.gov.cn/nw12344/20260515/270fa9966d644d3b9f1afbcac8aaa759.html",
      "category": "regional",
      "source": "上海市人民政府"
    },
    {
      "report_date": "2026-05-15",
      "fingerprint": "47e8499b5fdf7a8c2bc1dc7ae7f9b0f3f49d5bc9",
      "title": "在文化里相遇 在潮流里尽兴 首届中国新文创市集5月15日启幕",
      "url": "https://www.beijing.gov.cn/fuwu/bmfw/sy/jrts/202605/t20260515_4651701.html",
      "category": "regional",
      "source": "首都之窗"
    },
    {
      "report_date": "2026-05-15",
      "fingerprint": "cd017439cca39b8b87e6da05344a98899e6601da",
      "title": "国际品牌“引进来” 中国好物“走出去” 北京商圈越来越有国际范儿",
      "url": "https://www.beijing.gov.cn/ywdt/gzdt/202605/t20260515_4651690.html",
      "category": "regional",
      "source": "首都之窗"
    },
    {
      "report_date": "2026-05-15",
      "fingerprint": "3985fb705737110817c9092087c8b4bf1f7e99f6",
      "title": "北京四大平台便利服务来京外籍人士 用户诉求线上直达“接诉即办”",
      "url": "https://www.beijing.gov.cn/fuwu/bmfw/sy/jrts/202605/t20260515_4651704.html",
      "category": "regional",
      "source": "首都之窗"
    },
    {
      "report_date": "2026-05-15",
      "fingerprint": "0d227eb85269dec3ba895514b9d1c88700e44e2c",
      "title": "上海市人民政府办公厅关于印发《上海市深化“一网通办”改革 打造“高效办成一件事”最佳体验地行动方案》的通知",
      "url": "https://www.shanghai.gov.cn/nw12344/20260515/b393a352da314b92b42730755baf2d25.html",
      "category": "regional",
      "source": "上海市人民政府"
    },
    {
      "report_date": "2026-05-16",
      "fingerprint": "92c5dc331dc6ebbb6dc7a65632553cb87a81588c",
      "title": "一次开药管仨月！慢性病长期处方新政落地",
      "url": "https://news.cctv.com/2026/05/16/ARTIhjPjaNGCAEUxv7KerM6N260516.shtml?spm=C94212.PBZrLs0D62ld.EKoevbmLqVHC.15",
      "category": "top_politics",
      "source": "央视网"
    },
    {
      "report_date": "2026-05-16",
      "fingerprint": "17c7b30588cf476302315ce425061ce332d6610f",
      "title": "“需要共同书写的时代答卷”——习近平主席同特朗普总统会晤侧记",
      "url": "https://www.gov.cn/yaowen/liebiao/202605/content_7068870.htm",
      "category": "policy",
      "source": "中国政府网"
    },
    {
      "report_date": "2026-05-16",
      "fingerprint": "599971e7429c7ef2ac5ee04cb1f2b06e96be7dca",
      "title": "微镜头·中美元首在北京举行会谈",
      "url": "https://www.gov.cn/yaowen/liebiao/202605/content_7069056.htm",
      "category": "policy",
      "source": "中国政府网"
    },
    {
      "report_date": "2026-05-16",
      "fingerprint": "fdc54df8b6d59209a8847b914da56f25ff40c38e",
      "title": "怀柔科学城“大国重器”打造科创策源地 本市重大科技基础设施平台密度全国居首",
      "url": "https://www.beijing.gov.cn/ywdt/gzdt/202605/t20260516_4653693.html",
      "category": "regional",
      "source": "首都之窗"
    },
    {
      "report_date": "2026-05-16",
      "fingerprint": "4c6ec24f0ccffb38bd5dc4c11150e83defdf6acc",
      "title": "国内首个开源开放AI智能体共性基础设施发布 破解当前智能体产业四大痛点",
      "url": "https://www.beijing.gov.cn/fuwu/lqfw/gggs/202605/t20260516_4653692.html",
      "category": "regional",
      "source": "首都之窗"
    },
    {
      "report_date": "2026-05-16",
      "fingerprint": "829a90a9e605c3caca25f8eee0fcaead15fd9eaa",
      "title": "五月京城上演文创嘉年华 持续10天 全程免费",
      "url": "https://www.beijing.gov.cn/fuwu/bmfw/sy/jrts/202605/t20260516_4653694.html",
      "category": "regional",
      "source": "首都之窗"
    },
    {
      "report_date": "2026-05-16",
      "fingerprint": "af332f6276c3f836a6ec4a5fcfe101031939f536",
      "title": "一批世界500强医药巨头纷纷入驻国际医药创新公园 “北京服务”让外企投下“信任票”",
      "url": "https://www.beijing.gov.cn/fuwu/lqfw/gggs/202605/t20260516_4653691.html",
      "category": "regional",
      "source": "首都之窗"
    },
    {
      "report_date": "2026-05-17",
      "fingerprint": "59cbfae1372b3f42031848397fb2342b9d54f6e0",
      "title": "国产赛级汽油来了！103号到底有何特殊之处？",
      "url": "https://news.cctv.com/2026/05/18/ARTIz523bVXcpM0bTxJBaNw0260518.shtml",
      "category": "top_politics",
      "source": "央视网"
    },
    {
      "report_date": "2026-05-17",
      "fingerprint": "f1fa97a483752847b799931276bb03b13420fc3c",
      "title": "习近平就推动哲学社会科学高质量发展作出重要指示",
      "url": "https://www.gov.cn/yaowen/liebiao/202605/content_7069131.htm",
      "category": "policy",
      "source": "中国政府网"
    },
    {
      "report_date": "2026-05-17",
      "fingerprint": "20812e961d34c520017a64d9f6f134672a8325f1",
      "title": "《五星出东方》首演五周年首启8K“超现场”直播 京产精品剧目演出直达全国10余省市",
      "url": "https://www.beijing.gov.cn/fuwu/bmfw/sy/jrts/202605/t20260518_4654954.html",
      "category": "regional",
      "source": "首都之窗"
    },
    {
      "report_date": "2026-05-17",
      "fingerprint": "644eb82d1009924e8e9434cc8955c8224f02e268",
      "title": "国家统计局2026年常规统计督察第2统计督察组公布受理反映上海市统计违纪违法行为举报方式",
      "url": "https://www.shanghai.gov.cn/nw12344/20260518/d926a78ab56e4ebda866426b7d8a4940.html",
      "category": "regional",
      "source": "上海市人民政府"
    },
    {
      "report_date": "2026-05-17",
      "fingerprint": "a2a12f8df9f13cafccb445172bd8d195d2ec454c",
      "title": "收到总书记回信两年 长城脚下山乡蜕变 石峡村交出“振兴答卷”",
      "url": "https://www.beijing.gov.cn/ywdt/yaowen/202605/t20260518_4654928.html",
      "category": "regional",
      "source": "首都之窗"
    },
    {
      "report_date": "2026-05-17",
      "fingerprint": "7aacd70829297db42fe12b4a6d2ec0a93d320ca7",
      "title": "北京领跑中国人工智能50强",
      "url": "https://www.beijing.gov.cn/fuwu/lqfw/gggs/202605/t20260518_4654932.html",
      "category": "regional",
      "source": "首都之窗"
    },
    {
      "report_date": "2026-05-17",
      "fingerprint": "26e4acb0d310031ff50fcad881a86a3643fee2cd",
      "title": "北京专精特新中小企业实现“三破万”",
      "url": "https://www.beijing.gov.cn/ywdt/gzdt/202605/t20260518_4654933.html",
      "category": "regional",
      "source": "首都之窗"
    },
    {
      "report_date": "2026-05-17",
      "fingerprint": "fc49666ecedf97f803559335151cbffaa519a252",
      "title": "人民锐评：教培倒卖学生信息需追问每一环责任",
      "url": "https://opinion.people.com.cn/n1/2026/0517/c1003-40721284.html",
      "category": "comments",
      "source": "人民网评论"
    },
    {
      "report_date": "2026-05-17",
      "fingerprint": "3507b35c4c7527217a49f9260f280a59b9cc9a38",
      "title": "树立正确的战略认知",
      "url": "http://www.news.cn/comments/20260518/cf18228aa552454995682d8388c043fb/c.html",
      "category": "comments",
      "source": "新华网评论"
    },
    {
      "report_date": "2026-05-17",
      "fingerprint": "7123b781792c648117d468fd2280b981d3d08b97",
      "title": "7年两轮中央生态环保督察守护祖国绿水青山",
      "url": "http://www.xinhuanet.com/comments/donglu.htm",
      "category": "comments",
      "source": "新华网评论"
    },
    {
      "report_date": "2026-05-18",
      "fingerprint": "33fc3bdad8d564836fda9b73d7bf52fb7224d212",
      "title": "实景演绎、数字赋能、文创开发：让文物活起来",
      "url": "https://news.cctv.com/2026/05/19/ARTIWUB3HrydrOIMzXoFgVAU260518.shtml",
      "category": "top_politics",
      "source": "央视网"
    },
    {
      "report_date": "2026-05-18",
      "fingerprint": "27afb9f57ce512cfa722747d0c518cb85d12e034",
      "title": "开局起步“十五五”系列主题新闻发布会",
      "url": "https://www.news.cn/zt/swwxlztfbh/index.html",
      "category": "top_politics",
      "source": "新华社"
    },
    {
      "report_date": "2026-05-18",
      "fingerprint": "3a87ded550e3f9344238881e751eac97a7724acd",
      "title": "“清清黄河”行进式报道",
      "url": "https://www.news.cn/specials.html",
      "category": "top_politics",
      "source": "新华社"
    },
    {
      "report_date": "2026-05-18",
      "fingerprint": "4ca997c1d9f8d3726112af7662edc45174627186",
      "title": "郑栅洁主任会见波音公司总裁兼首席执行官奥特伯格",
      "url": "https://www.ndrc.gov.cn/xwdt/xwfb/202605/t20260518_1405245.html",
      "category": "policy",
      "source": "国家发展改革委"
    },
    {
      "report_date": "2026-05-18",
      "fingerprint": "cdfe53802de2146e37995fcfd6dcf4c2d152a4dc",
      "title": "李春临副主任会见通用电气航空航天集团董事长兼首席执行官卡尔普",
      "url": "https://www.ndrc.gov.cn/xwdt/xwfb/202605/t20260518_1405244.html",
      "category": "policy",
      "source": "国家发展改革委"
    },
    {
      "report_date": "2026-05-18",
      "fingerprint": "ec69369010b8578bda1ec49e567d3691355d3f4c",
      "title": "去年全国离境退税销售额同比增近1倍 北京实现“购物即退税 全城任意退”",
      "url": "https://www.beijing.gov.cn/ywdt/gzdt/202605/t20260519_4656670.html",
      "category": "regional",
      "source": "首都之窗"
    },
    {
      "report_date": "2026-05-18",
      "fingerprint": "9f90dce725f0c738465bb73e85eac4d66880fa38",
      "title": "“开局起步‘十五五’”上海专场新闻发布会举行，龚正作主题发布并答记者问",
      "url": "https://www.shanghai.gov.cn/nw12344/20260518/21e522304ab4498e97d921b03fa4db7a.html",
      "category": "regional",
      "source": "上海市人民政府"
    },
    {
      "report_date": "2026-05-18",
      "fingerprint": "7eb1c8b169bd5d445be134d48484c796f7c95561",
      "title": "本市推出22项举措优化人才服务与劳动者权益保障 鼓励“一人公司”等创业新模式",
      "url": "https://www.beijing.gov.cn/ywdt/gzdt/202605/t20260519_4656664.html",
      "category": "regional",
      "source": "首都之窗"
    },
    {
      "report_date": "2026-05-18",
      "fingerprint": "396242681e3839981453093e74b4faf747791b44",
      "title": "一批科学智能成果加速落地 本市搭建领跑智能科研平台体系",
      "url": "https://www.beijing.gov.cn/ywdt/gzdt/202605/t20260519_4656634.html",
      "category": "regional",
      "source": "首都之窗"
    },
    {
      "report_date": "2026-05-18",
      "fingerprint": "b43569bdc276e96a01d9e78f4bddd1fec51fa594",
      "title": "一场雨下了常年同期4倍的量 南郊观象台刷新最早暴雨日纪录",
      "url": "https://www.beijing.gov.cn/fuwu/bmfw/sy/jrts/202605/t20260519_4656667.html",
      "category": "regional",
      "source": "首都之窗"
    },
    {
      "report_date": "2026-05-18",
      "fingerprint": "4d1cf17deb383275f7eb0fc9f545e1d7851dd924",
      "title": "以相向而行的行动落实好重要共识",
      "url": "http://www.news.cn/comments/20260518/4463b75ca67f438f9694df1f8ff4ac89/c.html",
      "category": "comments",
      "source": "新华网评论"
    },
    {
      "report_date": "2026-05-18",
      "fingerprint": "82faf7f180825704ad6cf4cd46f85dd62ca8695e",
      "title": "任仲平：立党为公、为民造福、科学决策、真抓实干",
      "url": "https://opinion.people.com.cn/n1/2026/0518/c461529-40721407.html",
      "category": "comments",
      "source": "人民网评论"
    },
    {
      "report_date": "2026-05-18",
      "fingerprint": "5a4a9276312bc87c7b46f3ee5c62bf1f683cd4a2",
      "title": "新华网视评丨“种花家”的绿化，硬核又浪漫",
      "url": "https://www.news.cn/comments/20260518/63133d95197548019ead18978c590095/c.html",
      "category": "comments",
      "source": "新华网评论"
    },
    {
      "report_date": "2026-05-19",
      "fingerprint": "082a4bd7b76ce25c42a792ee0fa6259bf08809b2",
      "title": "开启夏收，收官春播——在希望的田野上",
      "url": "https://news.cctv.com/2026/05/20/ARTInZuKLr8XLPLUrm5hExVs260519.shtml",
      "category": "top_politics",
      "source": "央视网"
    },
    {
      "report_date": "2026-05-19",
      "fingerprint": "4733f483f5ba7ba46b076c9a6942f40e727dd607",
      "title": "习近平文化思想引领旅游强国建设",
      "url": "https://www.gov.cn/yaowen/liebiao/202605/content_7069398.htm",
      "category": "policy",
      "source": "中国政府网"
    },
    {
      "report_date": "2026-05-19",
      "fingerprint": "0d385cd2d4005ec6f3b1c7b5bc5bddd3fba61471",
      "title": "经济数据速览：7组数字看1—4月份中国经济",
      "url": "https://www.gov.cn/zhengce/jiedu/tujie/202605/content_7069278.htm",
      "category": "policy",
      "source": "中国政府网"
    },
    {
      "report_date": "2026-05-19",
      "fingerprint": "1d4e65906a400a017bced378e8e95223efe15d86",
      "title": "贯通成果转化全链条服务体系 北京市推动基础研究成果加速走向市场",
      "url": "https://www.beijing.gov.cn/fuwu/lqfw/gggs/202605/t20260520_4658232.html",
      "category": "regional",
      "source": "首都之窗"
    },
    {
      "report_date": "2026-05-19",
      "fingerprint": "302d1cecdc03169b3a267908a34b681f0b906664",
      "title": "浦东新区人民政府办公室关于印发《浦东新区全面深化成本预算绩效管理改革实施方案（2026-2028年）》的通知",
      "url": "https://www.shanghai.gov.cn/nw12344/20260519/99d54805611548be9306a449e9bf85ee.html",
      "category": "regional",
      "source": "上海市人民政府"
    },
    {
      "report_date": "2026-05-19",
      "fingerprint": "9f83bbf09290db5f1620a2785b942b1433e16362",
      "title": "市政府2026年安排25项立法项目 包括博物馆条例、民营经济促进条例、人工智能产业发展条例等",
      "url": "https://www.beijing.gov.cn/ywdt/gzdt/202605/t20260520_4658234.html",
      "category": "regional",
      "source": "首都之窗"
    },
    {
      "report_date": "2026-05-19",
      "fingerprint": "c3f02613cdc32a3faaa12ec9691605b470808595",
      "title": "前四月北京经济运行稳中有进 全市规模以上工业增加值同比增长4.2%",
      "url": "https://www.beijing.gov.cn/gongkai/shuju/sjjd/202605/t20260520_4658233.html",
      "category": "regional",
      "source": "首都之窗"
    },
    {
      "report_date": "2026-05-19",
      "fingerprint": "a10a4eaa90d77bfdaf04922dc49a7aa248d16863",
      "title": "从带娃到照护老人 干活不再只凭经验 “北京家政”服务标准化",
      "url": "https://www.beijing.gov.cn/ywdt/gzdt/202605/t20260520_4658235.html",
      "category": "regional",
      "source": "首都之窗"
    },
    {
      "report_date": "2026-05-19",
      "fingerprint": "d61ab7b2397aeb8f324bc731cb6d525e6ce87bef",
      "title": "人民锐评：以监管“无感”厚植民企发展安全感",
      "url": "https://opinion.people.com.cn/n1/2026/0519/c436867-40723151.html",
      "category": "comments",
      "source": "人民网评论"
    },
    {
      "report_date": "2026-05-19",
      "fingerprint": "4509c818069435220b8379483124af843a4a97de",
      "title": "做优“在场感” 做强新经济",
      "url": "https://www.news.cn/comments/20260519/e18e1a6bbbd742418d023bcfbf8b36e5/c.html",
      "category": "comments",
      "source": "新华网评论"
    },
    {
      "report_date": "2026-05-19",
      "fingerprint": "bfcf9e478da8efbd7c0a748dae86eb9b9c31f162",
      "title": "“咱农民也能把自己活成诗”",
      "url": "https://www.news.cn/comments/20260519/a741fd5cba744853937521f12c23c5e4/c.html",
      "category": "comments",
      "source": "新华网评论"
    },
    {
      "report_date": "2026-05-20",
      "fingerprint": "4a67e5f48b78771dd6238cf5971b7679e1aec9f3",
      "title": "1—4月 全国一般公共预算收入同比增长3.5%",
      "url": "https://news.cctv.com/2026/05/21/ARTIan6xC5PGRsaqJwPHU0aK260521.shtml",
      "category": "top_politics",
      "source": "央视网"
    },
    {
      "report_date": "2026-05-20",
      "fingerprint": "902d9cca1ccd1852000ecea0a429733c8715cef6",
      "title": "郑栅洁主任主持召开民营企业座谈会 围绕当前经济形势及宏观政策落实情况听取意见建议",
      "url": "https://www.ndrc.gov.cn/xwdt/xwfb/202605/t20260520_1405329.html",
      "category": "policy",
      "source": "国家发展改革委"
    },
    {
      "report_date": "2026-05-20",
      "fingerprint": "09b891fdcf7a8d2d774206b78d616374dd92dd18",
      "title": "习近平同俄罗斯总统普京共同会见记者",
      "url": "https://www.gov.cn/yaowen/liebiao/202605/content_7069677.htm",
      "category": "policy",
      "source": "中国政府网"
    },
    {
      "report_date": "2026-05-20",
      "fingerprint": "611593efc41e70d7bb10edf7d91043ad1c94ec17",
      "title": "习近平同俄罗斯总统普京会谈",
      "url": "https://www.gov.cn/yaowen/liebiao/202605/content_7069661.htm",
      "category": "policy",
      "source": "中国政府网"
    },
    {
      "report_date": "2026-05-20",
      "fingerprint": "1317182266ca69268f3b7816c6bb05348bd3f65e",
      "title": "共同出席“中俄教育年”开幕式并致辞",
      "url": "https://www.gov.cn/yaowen/liebiao/202605/content_7069697.htm",
      "category": "policy",
      "source": "中国政府网"
    },
    {
      "report_date": "2026-05-20",
      "fingerprint": "1d2eaf11c8b54409a995381f35acba5d434b7bbd",
      "title": "人民锐评：建而不用，民生工程岂能成“盆景”！",
      "url": "https://opinion.people.com.cn/n1/2026/0521/c436867-40724248.html",
      "category": "comments",
      "source": "人民网评论"
    },
    {
      "report_date": "2026-05-21",
      "fingerprint": "a9718a073d9c6bfdb4c86d9023ad4d3948c6f04c",
      "title": "南方多地降雨持续 各地各部门积极应对",
      "url": "https://news.cctv.com/2026/05/22/ARTIphZT37yaF4ZR91W7R7Mn260522.shtml",
      "category": "top_politics",
      "source": "央视网"
    },
    {
      "report_date": "2026-05-21",
      "fingerprint": "ddbd34846ea0053ea615eb54f23c658bfd4ff08b",
      "title": "2026年5月21日国内成品油价格调整",
      "url": "https://www.ndrc.gov.cn/xwdt/xwfb/202605/t20260521_1405346.html",
      "category": "policy",
      "source": "国家发展改革委"
    },
    {
      "report_date": "2026-05-21",
      "fingerprint": "cd0664a6123cd8bdbf8a7bf02688981b56452050",
      "title": "“中国省市文化产业发展指数”发布 北京连续十年保持全国第一",
      "url": "https://www.beijing.gov.cn/ywdt/gzdt/202605/t20260522_4661628.html",
      "category": "regional",
      "source": "首都之窗"
    },
    {
      "report_date": "2026-05-21",
      "fingerprint": "76a98f73dd086ac867e11fe9edeb5354d90dc71e",
      "title": "上海市发展和改革委员会关于车用汽、柴油价格的通知（2026年5月21日）",
      "url": "https://www.shanghai.gov.cn/nw12344/20260521/6302067be94a47079e12205898288d56.html",
      "category": "regional",
      "source": "上海市人民政府"
    },
    {
      "report_date": "2026-05-21",
      "fingerprint": "cbf6b21a4857d68a8821e836bce8fa9170807315",
      "title": "首都文化产业高质量发展成果亮相深圳文博会 北京展区现代与传统交相辉映",
      "url": "https://www.beijing.gov.cn/fuwu/bmfw/sy/jrts/202605/t20260522_4661626.html",
      "category": "regional",
      "source": "首都之窗"
    },
    {
      "report_date": "2026-05-21",
      "fingerprint": "4193c50f7b8e8c1f0f073a162fb6142cb73ab23d",
      "title": "国家统计局2026年常规统计督察第1统计督察组进驻北京市开展统计督察",
      "url": "https://www.beijing.gov.cn/ywdt/gzdt/202605/t20260521_4661216.html",
      "category": "regional",
      "source": "首都之窗"
    },
    {
      "report_date": "2026-05-21",
      "fingerprint": "f70affd4b25fc4bf6ef572b5691aeb113a358b5c",
      "title": "人民锐评：\"变态辣\"到\"微辣\"，中国靠什么打好\"化肥保卫战\"",
      "url": "https://opinion.people.com.cn/n1/2026/0521/c436867-40724670.html",
      "category": "comments",
      "source": "人民网评论"
    },
    {
      "report_date": "2026-05-21",
      "fingerprint": "bcc7b63788da904468464aa276110d15c38aeba4",
      "title": "新华网视评｜灾难不是流量生意",
      "url": "https://www.news.cn/comments/20260521/b36076aac66d4951937ea1bd495998b6/c.html",
      "category": "comments",
      "source": "新华网评论"
    },
    {
      "report_date": "2026-05-21",
      "fingerprint": "5e10a57334927a24b2c3444c0b45bdfcd984010b",
      "title": "新华网三评之一：以敬畏之心守护科学诚信",
      "url": "https://www.news.cn/comments/20260521/b8128341c42143c88ed60146e3ff4d2d/c.html",
      "category": "comments",
      "source": "新华网评论"
    },
    {
      "report_date": "2026-05-22",
      "fingerprint": "dec6c4ec4f82a021b8cdcacc803b50dccc611c46",
      "title": "约5万亿元投资！我国城市地下管网规模全球第一",
      "url": "https://news.cctv.com/2026/05/23/ARTI8fDfhvNxvZB5qdeSLQ78260523.shtml",
      "category": "top_politics",
      "source": "央视网"
    },
    {
      "report_date": "2026-05-22",
      "fingerprint": "e26c6f54342052fb33f7197c6e8e1023a175358e",
      "title": "习近平：做强做优做大实体经济",
      "url": "https://www.gov.cn/yaowen/liebiao/202605/content_7068939.htm",
      "category": "policy",
      "source": "中国政府网"
    },
    {
      "report_date": "2026-05-22",
      "fingerprint": "631a298f8dc0bba0bc86d763570143ebf775d9d0",
      "title": "习近平生态文明思想引领生物多样性保护事业开创新局面",
      "url": "https://www.gov.cn/yaowen/liebiao/202605/content_7069989.htm",
      "category": "policy",
      "source": "中国政府网"
    },
    {
      "report_date": "2026-05-22",
      "fingerprint": "4bacaeb1d4aa9832ef4c9e18d8599f624803014a",
      "title": "国家发展改革委举行5月份新闻发布会",
      "url": "https://www.ndrc.gov.cn/xwdt/xwfb/202605/t20260522_1405405.html",
      "category": "policy",
      "source": "国家发展改革委"
    },
    {
      "report_date": "2026-05-22",
      "fingerprint": "1c3fe4b8e5e4e1d5f6f9cc3bb0af1cce7579bb27",
      "title": "2026年前4个月邮政行业寄递业务量同比增长4.1%",
      "url": "https://www.gov.cn/zhengce/jiedu/tujie/202605/content_7069751.htm",
      "category": "policy",
      "source": "中国政府网"
    },
    {
      "report_date": "2026-05-22",
      "fingerprint": "a244f6cbd005a5754cf47dc1417533157540fcc1",
      "title": "上海市人民政府办公厅关于开展第三届“上海慈善奖”评选工作的通知",
      "url": "https://www.shanghai.gov.cn/nw12344/20260522/8e2926f823554bc09f42894dcbbb715e.html",
      "category": "regional",
      "source": "上海市人民政府"
    },
    {
      "report_date": "2026-05-22",
      "fingerprint": "e27c8d8182857e9f9eaf89d22f637a95ced3918d",
      "title": "壹时评：法治春风护航 民企体感更踏实",
      "url": "https://opinion.people.com.cn/n1/2026/0522/c223228-40725438.html",
      "category": "comments",
      "source": "人民网评论"
    },
    {
      "report_date": "2026-05-22",
      "fingerprint": "f663c1f29a010999e3be2312081d6e7948ef2f87",
      "title": "新华网三评之三：毕业论文审核，不能过度依赖AI",
      "url": "https://www.news.cn/comments/20260523/b5e45ff2767a4c6f860d93d5a27e10fe/c.html",
      "category": "comments",
      "source": "新华网评论"
    },
    {
      "report_date": "2026-05-22",
      "fingerprint": "46b58061b7e28df3356fa9c74064076c4bb0a775",
      "title": "新华网评：自行车进地铁，值得点赞",
      "url": "https://www.news.cn/comments/20260522/8df4b4490ede4ab0a0501364ea3de656/c.html",
      "category": "comments",
      "source": "新华网评论"
    },
    {
      "report_date": "2026-05-22",
      "fingerprint": "c5e1b937e4529acaeff12154558cee2eed7a05ef",
      "title": "新华网三评之二：论文署名岂能沦为“唐僧肉”",
      "url": "https://www.news.cn/comments/20260522/02db6b1b5833432bbb725a4d7ba6ed64/c.html",
      "category": "comments",
      "source": "新华网评论"
    },
    {
      "report_date": "2026-05-23",
      "fingerprint": "e045605cfe9279044f1621176a9372e87688c23f",
      "title": "我国万米深海材料腐蚀试验再破纪录",
      "url": "https://news.cctv.com/2026/05/24/ARTIoGtqjHpMQWp0iWT7affw260524.shtml",
      "category": "top_politics",
      "source": "央视网"
    },
    {
      "report_date": "2026-05-23",
      "fingerprint": "3b0d9a406b41e4e5f68c5c2f912c380f349dc89e",
      "title": "习近平对山西长治市沁源县一煤矿瓦斯爆炸事故作出重要指示",
      "url": "https://www.gov.cn/yaowen/liebiao/202605/content_7070013.htm",
      "category": "policy",
      "source": "中国政府网"
    },
    {
      "report_date": "2026-05-23",
      "fingerprint": "3fa195e9e2cb33959989890203a91ab5ac2f3395",
      "title": "落实总书记重要指示 维护人民群众生命财产安全",
      "url": "https://www.gov.cn/yaowen/liebiao/202605/content_7070074.htm",
      "category": "policy",
      "source": "中国政府网"
    },
    {
      "report_date": "2026-05-23",
      "fingerprint": "e14675bc5b278794ac5071e834f57aa466045fb9",
      "title": "潮白河国家森林公园先行启动区2026年建成 地铁22号线年底开通 京津冀三地协同发展迈上新台阶",
      "url": "https://www.beijing.gov.cn/ywdt/yaowen/202605/t20260523_4663543.html",
      "category": "regional",
      "source": "首都之窗"
    },
    {
      "report_date": "2026-05-23",
      "fingerprint": "5819f0e37d323a8ad7bd7d3a281105373cf6f5c7",
      "title": "服务在先普法先行 解决“家门口”的治理难题 社区里多了一抹“城管蓝”",
      "url": "https://www.beijing.gov.cn/ywdt/gzdt/202605/t20260523_4663544.html",
      "category": "regional",
      "source": "首都之窗"
    },
    {
      "report_date": "2026-05-23",
      "fingerprint": "d3e146ff231c1d6ae5ac771bafd5e2556ebdc0ab",
      "title": "各地民俗风情闪耀首届中国新文创市集 朝阳公园一站逛遍文创宝藏",
      "url": "https://www.beijing.gov.cn/fuwu/bmfw/sy/jrts/202605/t20260523_4663548.html",
      "category": "regional",
      "source": "首都之窗"
    },
    {
      "report_date": "2026-05-23",
      "fingerprint": "1a5a44f745bb585e9a117f075dc6b4152a521b49",
      "title": "前沿科技成果亮相文博会 北京展现数智时代的日常新图景",
      "url": "https://www.beijing.gov.cn/fuwu/lqfw/gggs/202605/t20260523_4663546.html",
      "category": "regional",
      "source": "首都之窗"
    },
    {
      "report_date": "2026-05-24",
      "fingerprint": "d82a2431eca6a054ed57a5286bcf8456f55fcc51",
      "title": "生活垃圾、工业固废循环再利用 “无废城市”这样建成",
      "url": "https://news.cctv.com/2026/05/24/ARTIquklaJkMKJrhMYki8jp8260524.shtml",
      "category": "top_politics",
      "source": "央视网"
    },
    {
      "report_date": "2026-05-24",
      "fingerprint": "d8f7f3cff6c4edbac1f912c8f12af311e354d667",
      "title": "起步有力 协同发展开新局",
      "url": "https://www.beijing.gov.cn/gongkai/shuju/sjjd/202605/t20260525_4663842.html",
      "category": "regional",
      "source": "首都之窗"
    },
    {
      "report_date": "2026-05-24",
      "fingerprint": "07676e193ac01fb1b59cf70f9d64f768fe378451",
      "title": "本市深入推进22家重点医院周边交通综合治理 朝阳医院常营院区“堵心路”变“顺心路”",
      "url": "https://www.beijing.gov.cn/ywdt/gzdt/202605/t20260525_4663845.html",
      "category": "regional",
      "source": "首都之窗"
    },
    {
      "report_date": "2026-05-24",
      "fingerprint": "059fff107d0081a778a686cae222dce477d46f0c",
      "title": "便民回收机“吃垃圾返收益” 小程序一键预约上门回收 “集中回收日”进社区 北京“三维发力”让垃圾回收更便利",
      "url": "https://www.beijing.gov.cn/ywdt/gzdt/202605/t20260525_4663844.html",
      "category": "regional",
      "source": "首都之窗"
    },
    {
      "report_date": "2026-05-24",
      "fingerprint": "390c4927e1a72637752676bc99cf19b7ab167380",
      "title": "五年筑基 再启新程——北京“十四五”高质量发展综述",
      "url": "https://www.beijing.gov.cn/ywdt/yaowen/202605/t20260525_4663843.html",
      "category": "regional",
      "source": "首都之窗"
    },
    {
      "report_date": "2026-05-25",
      "fingerprint": "df1f432b1d1f3259f569ab5b3ef3184032b77d0a",
      "title": "我国发布伦理指引 规范人体基因数据研究",
      "url": "https://news.cctv.com/2026/05/25/ARTI818kUWzjcXJ8yO9DihqE260525.shtml",
      "category": "top_politics",
      "source": "央视网"
    },
    {
      "report_date": "2026-05-25",
      "fingerprint": "314a120759647512970eea7a85bb7cd4ea49574b",
      "title": "习近平同塞尔维亚总统武契奇会谈",
      "url": "https://www.gov.cn/yaowen/liebiao/202605/content_7070179.htm",
      "category": "policy",
      "source": "中国政府网"
    },
    {
      "report_date": "2026-05-25",
      "fingerprint": "542e015cafb0b10caf33e09572c6904a7cf02a8b",
      "title": "习近平为武契奇举行“友谊勋章”颁授仪式",
      "url": "https://www.gov.cn/yaowen/liebiao/202605/content_7070194.htm",
      "category": "policy",
      "source": "中国政府网"
    },
    {
      "report_date": "2026-05-25",
      "fingerprint": "3f546cc34d033e1ed30a3bd90a566507a166599b",
      "title": "关于共同推动落实四大全球倡议的联合声明",
      "url": "https://www.gov.cn/yaowen/liebiao/202605/content_7070184.htm",
      "category": "policy",
      "source": "中国政府网"
    },
    {
      "report_date": "2026-05-25",
      "fingerprint": "6911aae2acb853c5e0802bd50058101b8e579ac3",
      "title": "中塞关于持续推进构建新时代中塞命运共同体的联合声明",
      "url": "https://www.gov.cn/yaowen/liebiao/202605/content_7070181.htm",
      "category": "policy",
      "source": "中国政府网"
    },
    {
      "report_date": "2026-05-25",
      "fingerprint": "652ecda0a52e9430c5d182a827d8d7e3ee294448",
      "title": "人民锐评：中考体测别迷信“神药”",
      "url": "https://opinion.people.com.cn/n1/2026/0525/c436867-40726630.html",
      "category": "comments",
      "source": "人民网评论"
    },
    {
      "report_date": "2026-05-25",
      "fingerprint": "26bb242311a440bba7ae4629e2846cab43bac89f",
      "title": "新华网视评丨以敬畏之心守护科学诚信",
      "url": "https://www.news.cn/comments/20260525/9de9b1a083ac4db384a3b30a93e28d55/c.html",
      "category": "comments",
      "source": "新华网评论"
    },
    {
      "report_date": "2026-05-25",
      "fingerprint": "0599a2f4bdff6aa3bd16a7dab8cb7977bf0204f5",
      "title": "安全不容失守 责任重于泰山",
      "url": "http://www.news.cn/comments/20260524/4af7566c5e8245ce894233d421baa02b/c.html",
      "category": "comments",
      "source": "新华网评论"
    },
    {
      "report_date": "2026-05-26",
      "fingerprint": "0519c5d42d2bd714e75cef00f3c2faaf5f913d02",
      "title": "住建部：未落户常住人口将纳入公租房保障范围",
      "url": "https://news.cctv.com/2026/05/27/ARTIBU0NBi2QuhbeNjLCP7ia260526.shtml",
      "category": "top_politics",
      "source": "央视网"
    },
    {
      "report_date": "2026-05-26",
      "fingerprint": "5f0ea7381f3447b6790f2b0b476f971ce29cabf4",
      "title": "习近平会见巴基斯坦总理夏巴兹",
      "url": "https://www.gov.cn/yaowen/liebiao/202605/content_7070158.htm",
      "category": "policy",
      "source": "中国政府网"
    },
    {
      "report_date": "2026-05-26",
      "fingerprint": "37d972c5488ab8b856733a978db75907a2eebaf6",
      "title": "截至2026年4月底，我国累计发电装机容量39.9亿千瓦",
      "url": "https://www.gov.cn/zhengce/jiedu/tujie/202605/content_7070224.htm",
      "category": "policy",
      "source": "中国政府网"
    },
    {
      "report_date": "2026-05-26",
      "fingerprint": "1ee15fc4b3a6fdafff31af6944444f5104cdf5cd",
      "title": "破解拍摄难题 拉动“视听+文旅”双向奔赴",
      "url": "https://www.beijing.gov.cn/ywdt/gzdt/202605/t20260527_4667694.html",
      "category": "regional",
      "source": "首都之窗"
    },
    {
      "report_date": "2026-05-26",
      "fingerprint": "c3f77b8238adf7ed526f3039612704b28a482e18",
      "title": "殷勇会见环球银行金融电信协会全球首席执行官",
      "url": "https://www.beijing.gov.cn/gongkai/ldhd/202605/t20260527_4667692.html",
      "category": "regional",
      "source": "首都之窗"
    },
    {
      "report_date": "2026-05-26",
      "fingerprint": "8f4e457d75733afb3e1efb76833e968641d6e792",
      "title": "前4月本市财政收入完成2689.1亿元 科技支出同比保持两位数增长",
      "url": "https://www.beijing.gov.cn/gongkai/shuju/sjjd/202605/t20260527_4667695.html",
      "category": "regional",
      "source": "首都之窗"
    },
    {
      "report_date": "2026-05-26",
      "fingerprint": "9b5318f69fad73d36aacac5f1b9b80cd54091f21",
      "title": "出台一系列扶持政策吸引青年人才来京创新创业扎根发展 本市打造“10号线人才活力环”",
      "url": "https://www.beijing.gov.cn/ywdt/gzdt/202605/t20260527_4667700.html",
      "category": "regional",
      "source": "首都之窗"
    },
    {
      "report_date": "2026-05-26",
      "fingerprint": "a3548e32bdc291e6123e32b6975b02d2fe97afc3",
      "title": "人民锐评：铺天盖地的“碳水脸”，彻头彻尾的伪概念",
      "url": "https://opinion.people.com.cn/n1/2026/0525/c436867-40726882.html",
      "category": "comments",
      "source": "人民网评论"
    },
    {
      "report_date": "2026-05-26",
      "fingerprint": "1765bdfc71f9e090e7022f392511cd436ab09cdd",
      "title": "新华网视评丨论文署名岂能沦为“唐僧肉”",
      "url": "https://www.news.cn/comments/20260526/ec1d681452d04712ac2018999ccaa8a2/c.html",
      "category": "comments",
      "source": "新华网评论"
    },
    {
      "report_date": "2026-05-27",
      "fingerprint": "3a2fd85c6a2ca00c3cfd043f7959ca6aef89e103",
      "title": "绿电+智算 新技术新模式推动AI与能源“双向奔赴”",
      "url": "https://news.cctv.com/2026/05/28/ARTIafXPBw5qcxyygLE3uwUK260528.shtml",
      "category": "top_politics",
      "source": "央视网"
    },
    {
      "report_date": "2026-05-27",
      "fingerprint": "666e3ef0d1dfd51cce1fe19286d37d36cdee868d",
      "title": "树立和践行正确政绩观",
      "url": "https://www.news.cn/zt/slhjxzqzjg/index.html",
      "category": "top_politics",
      "source": "新华社"
    },
    {
      "report_date": "2026-05-27",
      "fingerprint": "fc3ba64714a1934a091c57ed801f4ddcbd4c7f67",
      "title": "2026年前4个月全国规模以上工业企业利润增长18.2%",
      "url": "https://www.gov.cn/zhengce/jiedu/tujie/202605/content_7070401.htm",
      "category": "policy",
      "source": "中国政府网"
    },
    {
      "report_date": "2026-05-27",
      "fingerprint": "7ae064d80376ab652f95be09c13a8f9719e87d37",
      "title": "总书记的人民情怀 | “必须深刻把握中国式现代化对教育、科技、人才的需求”",
      "url": "https://www.gov.cn/yaowen/liebiao/202605/content_7070448.htm",
      "category": "policy",
      "source": "中国政府网"
    },
    {
      "report_date": "2026-05-27",
      "fingerprint": "c6f9162a902c9c872758741c5a0320bd7d1cb677",
      "title": "滨水如画 乐享自然 给市民带来亲近自然、多元共享的乐享空间",
      "url": "https://www.beijing.gov.cn/ywdt/gzdt/202605/t20260528_4669512.html",
      "category": "regional",
      "source": "首都之窗"
    },
    {
      "report_date": "2026-05-27",
      "fingerprint": "382644c1662adfd0985e5c97388721e1bc81a393",
      "title": "上海市人民政府关于推进服务业扩能提质的实施意见",
      "url": "https://www.shanghai.gov.cn/nw12344/20260527/5da1b7004eab483186d16dedb31cf013.html",
      "category": "regional",
      "source": "上海市人民政府"
    },
    {
      "report_date": "2026-05-27",
      "fingerprint": "a5926de5a13053c7bda99da8df3a8360f622f283",
      "title": "25场论坛实现智能体“听会” AI创新力量将齐聚北京智源大会",
      "url": "https://www.beijing.gov.cn/fuwu/lqfw/gggs/202605/t20260528_4669514.html",
      "category": "regional",
      "source": "首都之窗"
    },
    {
      "report_date": "2026-05-27",
      "fingerprint": "536c670b80017a9234adfcf83bc8dc467ada7fa8",
      "title": "20位中青年德艺双馨艺术家获表彰 涵盖共13个艺术门类",
      "url": "https://www.beijing.gov.cn/ywdt/gzdt/202605/t20260528_4669516.html",
      "category": "regional",
      "source": "首都之窗"
    },
    {
      "report_date": "2026-05-27",
      "fingerprint": "224291e9c0dbc823d7ba991056aa5038e1d4a897",
      "title": "人民锐评：收起刻薄的放大镜，别让实干者流汗又流泪",
      "url": "https://opinion.people.com.cn/n1/2026/0526/c436867-40727769.html",
      "category": "comments",
      "source": "人民网评论"
    },
    {
      "report_date": "2026-05-27",
      "fingerprint": "273e383237038a75a1fa52ec75c78f5cc129b57c",
      "title": "新华网评：“山海关不住”的“东北超”，为什么这么火？",
      "url": "https://www.news.cn/comments/20260527/5f0e46d608a94253b50297bdf7c9f907/c.html",
      "category": "comments",
      "source": "新华网评论"
    },
    {
      "report_date": "2026-05-27",
      "fingerprint": "81216f2530fb92b2ac1ddd28d7cd52dfc77e183e",
      "title": "新华网视评丨毕业论文审核，不能过度依赖AI",
      "url": "https://www.news.cn/comments/20260527/18e7c8ada1fc4ed3a22f7eb423849e98/c.html",
      "category": "comments",
      "source": "新华网评论"
    },
    {
      "report_date": "2026-05-28",
      "fingerprint": "73148b95de109f2192b22bc92983b66540c0ac22",
      "title": "奔跑的三夏｜700公里抢收路背后的夏收保障网",
      "url": "https://news.cctv.com/2026/05/29/ARTINMSH8MXxYU2gmI2FDvRD260528.shtml",
      "category": "top_politics",
      "source": "央视网"
    },
    {
      "report_date": "2026-05-28",
      "fingerprint": "b56a030dffba1119a88f48d26e8da1ca00dbab59",
      "title": "习近平复信参加“共航蔚蓝：中美青年友谊行”活动的两国学生",
      "url": "https://www.gov.cn/yaowen/liebiao/202605/content_7070492.htm",
      "category": "policy",
      "source": "中国政府网"
    },
    {
      "report_date": "2026-05-28",
      "fingerprint": "fc482c774af921b642d89270a9733a9cd89744ef",
      "title": "《城市更新“十五五”规划》发布",
      "url": "https://www.gov.cn/zhengce/jiedu/tujie/202605/content_7070581.htm",
      "category": "policy",
      "source": "中国政府网"
    },
    {
      "report_date": "2026-05-28",
      "fingerprint": "e18f8672c2618e6d05865f9811b677776d49063e",
      "title": "本市发布推动城市高质量发展实施意见 2035年初步建成国际一流的和谐宜居之都",
      "url": "https://www.beijing.gov.cn/zhengce/zcjd/202605/t20260529_4671335.html",
      "category": "regional",
      "source": "首都之窗"
    },
    {
      "report_date": "2026-05-28",
      "fingerprint": "c41c73fd68d0c8936c8811f8526df129708402a5",
      "title": "服务赋能智造 两业强强联合",
      "url": "https://www.beijing.gov.cn/fuwu/lqfw/gggs/202605/t20260529_4671326.html",
      "category": "regional",
      "source": "首都之窗"
    },
    {
      "report_date": "2026-05-28",
      "fingerprint": "447f909eb29b31913b46e4f209d956a0867dd878",
      "title": "修复站前广场 新增非机动车停车位 开通微循环公交 45个地铁站完成接驳优化",
      "url": "https://www.beijing.gov.cn/fuwu/bmfw/sy/jrts/202605/t20260529_4671342.html",
      "category": "regional",
      "source": "首都之窗"
    },
    {
      "report_date": "2026-05-28",
      "fingerprint": "828d9b7b05cd7ffc8586bfd39cb062d622824711",
      "title": "串珠成链 水岸焕新 北京20个滨水空间项目将在年内开启改造提升",
      "url": "https://www.beijing.gov.cn/ywdt/yaowen/202605/t20260529_4671323.html",
      "category": "regional",
      "source": "首都之窗"
    },
    {
      "report_date": "2026-05-28",
      "fingerprint": "4e32b810cf80225f5a9bec15ae093c140093bcc8",
      "title": "5000美元换来5万棵树 跨越时代和国界的人性共情",
      "url": "https://opinion.people.com.cn/n1/2026/0528/c223228-40729403.html",
      "category": "comments",
      "source": "人民网评论"
    }
  ]
}